osfloor.py
openseafloor-1.1.dist-info/METADATA
openseafloor-1.1.dist-info/WHEEL
openseafloor-1.1.dist-info/top_level.txt
openseafloor-1.1.dist-info/RECORD
