Metadata-Version: 2.1
Name: openseafloor
Version: 1.1
Summary: Scrape floor prices from OpenSea
Home-page: UNKNOWN
Author: Sem Moolenschot
Author-email: sem@moolenschot.nl
License: MIT
Platform: UNKNOWN
Classifier: Programming Language :: Python :: 3.10
Classifier: License :: OSI Approved :: MIT License
Classifier: Operating System :: OS Independent
Requires-Dist: cloudscraper
Requires-Dist: json
